pystage/__init__.py
pystage/util.py
pystage/convert/__init__.py
pystage/convert/code_writer.py
pystage/convert/sb3.py
pystage/convert/sb3_templates.py
pystage/core/__init__.py
pystage/core/_base_sprite.py
pystage/core/_control.py
pystage/core/_events.py
pystage/core/_looks.py
pystage/core/_motion.py
pystage/core/_operators.py
pystage/core/_pen.py
pystage/core/_sensing.py
pystage/core/_sound.py
pystage/core/_variables.py
pystage/core/asking.py
pystage/core/assets.py
pystage/core/code_block.py
pystage/core/constants.py
pystage/core/gui.py
pystage/core/messages.py
pystage/core/monitors.py
pystage/core/sprite.py
pystage/core/stage.py
pystage/de/__init__.py
pystage/de/sprite.py
pystage/de/stage.py
pystage/en/__init__.py
pystage/en/sprite.py
pystage/en/stage.py
pystage/fonts/roboto-bold.ttf
pystage/fonts/roboto-light.ttf
pystage/fonts/roboto-regular.ttf
pystage/images/grid.svg
pystage/images/pen.png
pystage/images/say.png
pystage/images/think.png
pystage/images/zombie_idle.png
pystage/l10n/__init__.py
pystage/l10n/__main__.py
pystage/l10n/api.py
pystage/l10n/translations.py
pystage/sounds/dancehead2.wav
pystage/sounds/guitar.wav
pystage-0.1.1.dist-info/LICENSE
pystage-0.1.1.dist-info/METADATA
pystage-0.1.1.dist-info/WHEEL
pystage-0.1.1.dist-info/top_level.txt
pystage-0.1.1.dist-info/RECORD
