Metadata-Version: 2.1
Name: pystage
Version: 0.1.1
Summary: Scratch-like Python programming
Home-page: https://github.com/pystage/pystage
Author: Kai Eckert
Author-email: k.eckert@hs-mannheim.de
License: MIT
Project-URL: Bug Tracker, https://github.com/pystage/pystage/issues
Classifier: Programming Language :: Python :: 3
Classifier: License :: OSI Approved :: MIT License
Classifier: Operating System :: OS Independent
Requires-Python: >=3.6
License-File: LICENSE
Requires-Dist: pygame
Requires-Dist: jinja2
Requires-Dist: setuptools
